collide_circle/__init__.py
collide_circle/core.py
collide_circle-0.1.2.dist-info/licenses/LICENSE.txt
collide_circle-0.1.2.dist-info/METADATA
collide_circle-0.1.2.dist-info/WHEEL
collide_circle-0.1.2.dist-info/top_level.txt
collide_circle-0.1.2.dist-info/RECORD
