Metadata-Version: 2.4
Name: collide_circle
Version: 0.1.2
Summary: A simple Pygame utility for rectangle-circle collision detection.
Home-page: https://github.com/austinewoody/collide_circle
Author: Austine Onwubiko
Author-email: austineonwubiko@gmail.com
Classifier: Programming Language :: Python :: 3
Classifier: License :: OSI Approved :: MIT License
Classifier: Operating System :: OS Independent
Requires-Python: >=3.6
License-File: LICENSE.txt
Dynamic: author
Dynamic: author-email
Dynamic: classifier
Dynamic: description
Dynamic: description-content-type
Dynamic: home-page
Dynamic: license-file
Dynamic: requires-python
Dynamic: summary
